{"is_source_file": false, "format": "", "description": "", "external_files": [], "external_methods": [], "published": [], "classes": [], "methods": [], "calls": [], "search-terms": [], "state": 2, "file_id": 5, "knowledge_revision": 20, "git_revision": "edd6a03bcf37c553dce128dade8a1db8d1d64507", "hash": "d2b40d02d5f7873d8a6713bad837edd4", "format-version": 4, "code-base-name": "todo_frontend", "filename": "todo_frontend/public/index.html", "revision_history": [{"20": "edd6a03bcf37c553dce128dade8a1db8d1d64507"}]}